ulogger/__init__.py
ulogger/exceptions.py
ulogger/stackdriver.py
ulogger/syslog.py
ulogger/ulogger.py
ulogger-3.0.0.dist-info/LICENSE
ulogger-3.0.0.dist-info/METADATA
ulogger-3.0.0.dist-info/WHEEL
ulogger-3.0.0.dist-info/top_level.txt
ulogger-3.0.0.dist-info/RECORD
