Metadata-Version: 2.1
Name: ulogger
Version: 3.0.0
Summary: Micro logging library
Home-page: https://github.com/spotify/ulogger
Author: Lynn Root
Author-email: lynn@spotify.com
Maintainer: Lynn Root
Maintainer-email: lynn@spotify.com
License: Apache 2.0
Keywords: logging
Classifier: Development Status :: 5 - Production/Stable
Classifier: License :: OSI Approved :: Apache Software License
Classifier: Natural Language :: English
Classifier: Operating System :: POSIX :: Linux
Classifier: Operating System :: MacOS :: MacOS X
Classifier: Programming Language :: Python
Classifier: Programming Language :: Python :: 3
Classifier: Programming Language :: Python :: 3.7
Classifier: Programming Language :: Python :: 3.8
Classifier: Programming Language :: Python :: Implementation :: CPython
Classifier: Topic :: Software Development :: Libraries :: Python Modules
License-File: LICENSE
Requires-Dist: requests
Provides-Extra: stackdriver
Requires-Dist: google-cloud-logging ; extra == 'stackdriver'
